agensgraph/__init__.py
agensgraph/_edge.py
agensgraph/_graphid.py
agensgraph/_graphpath.py
agensgraph/_property.py
agensgraph/_vertex.py
agensgraph_python-1.0.1.dist-info/licenses/LICENSE
agensgraph_python-1.0.1.dist-info/METADATA
agensgraph_python-1.0.1.dist-info/WHEEL
agensgraph_python-1.0.1.dist-info/top_level.txt
agensgraph_python-1.0.1.dist-info/RECORD
