Metadata-Version: 2.4
Name: agensgraph-python
Version: 1.0.1
Summary: Psycopg2 type extension module for AgensGraph
Home-page: https://github.com/skaiworldwide-oss/agensgraph-drivers/python
Author: Umar Hayat
Author-email: skaisw@skaiworldwide.com
Maintainer: Umar Hayat
Maintainer-email: skaisw@skaiworldwide.com
License: Apache License Version 2.0
Keywords: agensgraph graph database postgresql driver
Classifier: Development Status :: 5 - Production/Stable
Classifier: Intended Audience :: Developers
Classifier: Topic :: Database
Classifier: License :: OSI Approved :: Apache Software License
Classifier: Programming Language :: Python :: 3
License-File: LICENSE
Requires-Dist: psycopg2>=2.5.4
Dynamic: author
Dynamic: author-email
Dynamic: classifier
Dynamic: description
Dynamic: description-content-type
Dynamic: home-page
Dynamic: keywords
Dynamic: license
Dynamic: license-file
Dynamic: maintainer
Dynamic: maintainer-email
Dynamic: requires-dist
Dynamic: summary
